{
  "tool_id": "liquibase",
  "tool_name": "Liquibase",
  "source_url": "https://docs.liquibase.com/",
  "doc_type": "official",
  "fetched_at": "2025-12-23T04:28:11.766863+00:00",
  "http_status": 200,
  "content_type_header": "text/html; charset=utf-8",
  "word_count": 441,
  "sections": [
    "Take the 2026 Database Change Survey",
    "Welcome to",
    "Liquibase documentation",
    "Advance your skills at your own pace",
    "Fundamentals of Liquibase",
    "Managing Liquibase Changelogs",
    "Common Liquibase Design Patterns",
    "Authoring Liquibase Changesets",
    "Share. Learn. \nConnect.",
    "Why make the switch?",
    "Feeling Stuck?\nNeed more help?"
  ],
  "code_block_count": 0
}