{
  "tool_id": "wandb",
  "tool_name": "Weights & Biases",
  "source_url": "https://docs.wandb.ai/",
  "doc_type": "official",
  "fetched_at": "2025-12-23T04:31:30.395795+00:00",
  "http_status": 200,
  "content_type_header": "text/html; charset=utf-8",
  "word_count": 244,
  "sections": [
    "Weights & Biases Documentation",
    "W&B Models",
    "Develop AI models",
    "W&B Weave",
    "Use AI models in your app",
    "W&B Inference",
    "Access foundation models",
    "W&B Training",
    "Post-train your models"
  ],
  "code_block_count": 0
}